qclight/__init__.py
qclight/__main__.py
qclight/circuit/__init__.py
qclight/circuit/bell.py
qclight/circuit/boolean_inner_product.py
qclight/circuit/circuit.py
qclight/circuit/half_adder.py
qclight/circuit/random.py
qclight/circuit/visual_circuit.py
qclight/error/__init__.py
qclight/gate/__init__.py
qclight/gate/gate.py
qclight/gate/h_gate.py
qclight/gate/i_gate.py
qclight/gate/x_gate.py
qclight/gate/z_gate.py
qclight/utils/__init__.py
qclight/visualizer/__init__.py
qclight/visualizer/circuit_visualizer.py
qclight/visualizer/connector.py
qclight-0.0.2.dist-info/LICENSE
qclight-0.0.2.dist-info/METADATA
qclight-0.0.2.dist-info/WHEEL
qclight-0.0.2.dist-info/entry_points.txt
qclight-0.0.2.dist-info/top_level.txt
qclight-0.0.2.dist-info/RECORD
