Metadata-Version: 2.1
Name: qclight
Version: 0.0.2
Summary: A lightweught quantum computing simulator
Author-email: TendTo <casablancaernesto@gmail.com>
License: Copyright (c) 2022 TendTo        
Project-URL: Homepage, https://tendto.github.io/QCLight/docs
Project-URL: Source, https://github.com/TendTo/QCLight
Project-URL: Tracker, https://github.com/TendTo/QCLight/issues
Keywords: quantum,quantum computing,numpy,algebra,qubit
Classifier: Development Status :: 1 - Planning
Classifier: Topic :: Scientific/Engineering :: Mathematics
Classifier: Topic :: Scientific/Engineering :: Physics
Classifier: License :: OSI Approved :: MIT License
Classifier: Programming Language :: Python
Classifier: Programming Language :: Python :: 3
Classifier: Programming Language :: Python :: 3 :: Only
Classifier: Programming Language :: Python :: 3.9
Classifier: Programming Language :: Python :: 3.10
Requires-Python: >=3.7
License-File: LICENSE
Requires-Dist: numpy (<=1.23.4)
Provides-Extra: docs
Requires-Dist: sphinx ; extra == 'docs'
Requires-Dist: sphinx-rtd-theme ; extra == 'docs'
Requires-Dist: sphinx-rtd-dark-mode ; extra == 'docs'
Requires-Dist: sphinx-autodoc-typehints ; extra == 'docs'
Provides-Extra: style
Requires-Dist: black ; extra == 'style'
Requires-Dist: bumpver ; extra == 'style'
Requires-Dist: pylint ; extra == 'style'
Requires-Dist: isort ; extra == 'style'
Requires-Dist: mypy ; extra == 'style'
Provides-Extra: test
Requires-Dist: pytest ; extra == 'test'
